MANIFEST.in
requirements.pip
setup.cfg
setup.py
krux/__init__.py
krux/cli.py
krux/constants.py
krux/logging.py
krux/stats.py
krux/util.py
krux/tornado/__init__.py
krux/tornado/application.py
krux/tornado/cli.py
krux/tornado/handlers.py
krux_stdlib.egg-info/PKG-INFO
krux_stdlib.egg-info/SOURCES.txt
krux_stdlib.egg-info/dependency_links.txt
krux_stdlib.egg-info/requires.txt
krux_stdlib.egg-info/top_level.txt
tests/__init__.py
tests/unit_tests/__init__.py
tests/unit_tests/test_cli.py
tests/unit_tests/test_handlers.py
tests/unit_tests/test_logging.py
tests/unit_tests/test_stats.py
tests/unit_tests/test_tornado_application.py
tests/unit_tests/test_util.py