Metadata-Version: 1.0
Name: krux-stdlib
Version: 0.8.1
Summary: Standard library of python modules used at Krux.
Home-page: https://github.com/krux/python-krux-stdlib
Author: Paul Lathrop
Author-email: paul@krux.com
License: License :: OSI Approved :: MIT License
Download-URL: https://github.com/krux/python-krux-stdlib/tarball/release/0.8.1
Platform: UNKNOWN
